{
    "nodes": [
        {
            "uid": "7417ce9f-05d4-469d-9c0e-f0412a2c9b45",
            "name": "Payal Thakur (MBA)",
            "company": "JobsOhio",
            "email": null
        },
        {
            "uid": "c0321748-fe1a-4ebc-874f-6ca40fd6bfef",
            "name": "Jason Ward",
            "company": "JobsOhio",
            "email": "ward@jobsohio.com"
        },
        {
            "uid": "42949678311",
            "name": "Jessica Villa-Cruz",
            "company": "jobsohio",
            "email": "villa-cruz@jobsohio.com"
        },
        {
            "uid": "51539608192",
            "name": "Joe Guenther",
            "company": "covermymeds",
            "email": "JGuenther@covermymeds.com"
        },
        {
            "uid": "4324",
            "name": "Matt Scantland",
            "company": "covermymeds",
            "email": "mscantland@covermymeds.com"
        }
    ],
    "edges": [
        {
            "source": "7417ce9f-05d4-469d-9c0e-f0412a2c9b45",
            "target": "c0321748-fe1a-4ebc-874f-6ca40fd6bfef",
            "relation": "L,C",
            "weight": 11
        },
        {
            "source": "c0321748-fe1a-4ebc-874f-6ca40fd6bfef",
            "target": "42949678311",
            "relation": "C",
            "weight": 1
        },
        {
            "source": "42949678311",
            "target": "51539608192",
            "relation": "E,E",
            "weight": 10
        },
        {
            "source": "51539608192",
            "target": "4324",
            "relation": "C",
            "weight": 1
        }
    ]
}